PacoteTesTe/PacoteTesTe.py
PacoteTesTe/__init__.py
Pacoteste/Pacoteste.py
Pacoteste/__init__.py
Pacoteste-0.1.dist-info/LICENSE
Pacoteste-0.1.dist-info/METADATA
Pacoteste-0.1.dist-info/WHEEL
Pacoteste-0.1.dist-info/top_level.txt
Pacoteste-0.1.dist-info/RECORD
